{
  "project_info": {
    "project_number": "736034334486",
    "firebase_url": "https://cashlipi-default-rtdb.firebaseio.com",
    "project_id": "cashlipi",
    "storage_bucket": "cashlipi.firebasestorage.app"
  },
  "client": [
    {
      "client_info": {
        "mobilesdk_app_id": "1:736034334486:android:8c1b7c178361b0724c5237",
        "android_client_info": {
          "package_name": "com.jrappspot.cashlipi"
        }
      },
      "oauth_client": [
        {
          "client_id": "736034334486-c10nct4fig04olov42i4245qufmr4vjk.apps.googleusercontent.com",
          "client_type": 1,
          "android_info": {
            "package_name": "com.jrappspot.cashlipi",
            "certificate_hash": "1479abb2be43c2505108f9a93c9915da2e19b11b"
          }
        },
        {
          "client_id": "736034334486-gu4keqsupj6v7tfeqproacubfvrjfj73.apps.googleusercontent.com",
          "client_type": 3
        }
      ],
      "api_key": [
        {
          "current_key": "AIzaSyDo3NUf6-_xPuuBbF2EYL-9DlDIio9_NqY"
        }
      ],
      "services": {
        "appinvite_service": {
          "other_platform_oauth_client": [
            {
              "client_id": "736034334486-gu4keqsupj6v7tfeqproacubfvrjfj73.apps.googleusercontent.com",
              "client_type": 3
            }
          ]
        }
      }
    }
  ],
  "configuration_version": "1"
}
